bcampe/__init__.py
bcampe/estilos/__init__.py
bcampe/estilos/estilos.py
bcampe/estilos/styles.css
bcampe/filtros/__init__.py
bcampe/filtros/filtros.py
bcampe/funcoes/__init__.py
bcampe/funcoes/funcoes.py
bcampe/graficos/__init__.py
bcampe/graficos/graficos.py
bcampe-0.95.dist-info/METADATA
bcampe-0.95.dist-info/WHEEL
bcampe-0.95.dist-info/top_level.txt
bcampe-0.95.dist-info/RECORD
