Metadata-Version: 2.4
Name: bcampe
Version: 0.95
Summary: Funções, estilos e gráficos utilizados na construção de soluções de BI
Author: brunocampello
Author-email: alancampiello@gmail.com
Classifier: Programming Language :: Python :: 3
Classifier: License :: OSI Approved :: MIT License
Requires-Dist: wheel
Requires-Dist: setuptools
Requires-Dist: streamlit
Requires-Dist: plotly
Requires-Dist: matplotlib
Requires-Dist: pandas
Dynamic: author
Dynamic: author-email
Dynamic: classifier
Dynamic: description-content-type
Dynamic: requires-dist
Dynamic: summary
